Metadata-Version: 1.1
Name: pihole
Version: 0.1.1
Summary: Python API for interacting with Pi-hole.
Home-page: https://github.com/fabaff/python-pi-hole
Author: Fabian Affolter
Author-email: fabian@affolter-engineering.ch
License: MIT
Download-URL: https://github.com/fabaff/python-pi-hole/releases
Platform: UNKNOWN
Classifier: Development Status :: 3 - Alpha
Classifier: Environment :: Console
Classifier: Intended Audience :: Developers
Classifier: License :: OSI Approved :: MIT License
Classifier: Operating System :: MacOS :: MacOS X
Classifier: Operating System :: Microsoft :: Windows
Classifier: Operating System :: POSIX
Classifier: Programming Language :: Python :: 3.5
Classifier: Topic :: Utilities
